collision/__init__.py
collision/collide.py
core/__init__.py
core/articulation.py
core/control.py
core/graph_coloring.py
core/inertia.py
core/model.py
core/particles.py
core/state.py
newton/__init__.py
newton/py.typed
newton/collision/__init__.py
newton/collision/collide.py
newton/core/__init__.py
newton/core/articulation.py
newton/core/control.py
newton/core/graph_coloring.py
newton/core/inertia.py
newton/core/model.py
newton/core/particles.py
newton/core/state.py
newton/examples/__init__.py
newton/examples/example_cloth_self_contact.py
newton/examples/example_quadruped.py
newton/licenses/unittest-parallel-LICENSE.txt
newton/solvers/__init__.py
newton/solvers/integrator.py
newton/solvers/integrator_euler.py
newton/solvers/integrator_featherstone.py
newton/solvers/integrator_vbd.py
newton/solvers/integrator_xpbd.py
newton/tests/__init__.py
newton/tests/__main__.py
newton/tests/test_collision.py
newton/tests/test_coloring.py
newton/tests/test_model.py
newton/tests/test_sim_grad_bounce_linear.py
newton/tests/test_sim_kinematics.py
newton/tests/unittest_utils.py
newton/thirdparty/__init__.py
newton/thirdparty/unittest_parallel.py
newton/utils/__init__.py
newton_physics-0.1.0.dist-info/licenses/LICENSE.md
solvers/__init__.py
solvers/integrator.py
solvers/integrator_euler.py
solvers/integrator_featherstone.py
solvers/integrator_vbd.py
solvers/integrator_xpbd.py
tests/__init__.py
tests/test_model.py
tests/unittest_utils.py
utils/__init__.py
newton_physics-0.1.0.dist-info/METADATA
newton_physics-0.1.0.dist-info/WHEEL
newton_physics-0.1.0.dist-info/top_level.txt
newton_physics-0.1.0.dist-info/RECORD
