Metadata-Version: 2.4
Name: newton-physics
Version: 0.1.0
Summary: A GPU-accelerated physics engine for robotics simulation
Author-email: Newton Developers <warp-python@nvidia.com>
License-Expression: Apache-2.0
Classifier: Development Status :: 3 - Alpha
Classifier: Intended Audience :: Developers
Classifier: Intended Audience :: Science/Research
Classifier: Natural Language :: English
Classifier: Programming Language :: Python :: 3
Classifier: Programming Language :: Python :: 3.9
Classifier: Programming Language :: Python :: 3.10
Classifier: Programming Language :: Python :: 3.11
Classifier: Programming Language :: Python :: 3.12
Classifier: Topic :: Scientific/Engineering
Requires-Python: >=3.9
License-File: LICENSE.md
Requires-Dist: warp-lang>=1.7.0.dev20250326
Provides-Extra: dev
Requires-Dist: coverage[toml]>=7.8.0; extra == "dev"
Requires-Dist: usd-core>=25.2.post1; platform_machine != "aarch64" and extra == "dev"
Provides-Extra: docs
Requires-Dist: sphinx; extra == "docs"
Requires-Dist: furo; extra == "docs"
Provides-Extra: all
Requires-Dist: coverage[toml]>=7.8.0; extra == "all"
Requires-Dist: usd-core>=25.2.post1; platform_machine != "aarch64" and extra == "all"
Requires-Dist: sphinx; extra == "all"
Requires-Dist: furo; extra == "all"
Dynamic: license-file
